aioservice/__init__.py
aioservice/common/__init__.py
aioservice/common/logger.py
aioservice/common/utils.py
aioservice/http/__init__.py
aioservice/http/controller.py
aioservice/http/requests.py
aioservice/http/service.py
aioservice/tests/__init__.py
aioservice/tests/base.py
aioservice/tests/controllers.py
aioservice/tests/test_http_service.py
aioservice/tests/test_versioned_service.py
aioservice-0.0.4.dist-info/DESCRIPTION.rst
aioservice-0.0.4.dist-info/METADATA
aioservice-0.0.4.dist-info/RECORD
aioservice-0.0.4.dist-info/WHEEL
aioservice-0.0.4.dist-info/metadata.json
aioservice-0.0.4.dist-info/top_level.txt
aioservice-0.0.4.dist-info/zip-safe
